iupy/__init__.py
iupy/misc.py
iupy/myconfig.py
iupy/network.py
iupy-0.2.1.dist-info/LICENSE
iupy-0.2.1.dist-info/METADATA
iupy-0.2.1.dist-info/WHEEL
iupy-0.2.1.dist-info/top_level.txt
iupy-0.2.1.dist-info/RECORD
