Metadata-Version: 2.1
Name: iupy
Version: 0.2.1
Summary: Ian Underwood Python kit
Home-page: https://github.com/iunderwood/iupy
Author: Ian A. Underwood
Author-email: ian@underwood-hq.org
License: MIT License
Platform: OS Independent
Classifier: Development Status :: 3 - Alpha
Classifier: Intended Audience :: Developers
Classifier: License :: OSI Approved :: MIT License
Classifier: Natural Language :: English
Classifier: Operating System :: OS Independent
Classifier: Programming Language :: Python :: 3
Classifier: Programming Language :: Python :: 3.8
Classifier: Programming Language :: Python :: 3.9
Classifier: Programming Language :: Python :: 3.10
Classifier: Programming Language :: Python :: 3.11
Classifier: Topic :: Utilities
Requires-Python: >=3.8
License-File: LICENSE
